tts_accelerator/__init__.py
tts_accelerator/core.py
tts_accelerator/temporary.py
tts_accelerator-1.0.4.dist-info/licenses/LICENSE
tts_accelerator-1.0.4.dist-info/METADATA
tts_accelerator-1.0.4.dist-info/WHEEL
tts_accelerator-1.0.4.dist-info/top_level.txt
tts_accelerator-1.0.4.dist-info/RECORD
