Metadata-Version: 2.4
Name: tts_accelerator
Version: 1.0.4
Summary: Real-time speech generation from short to massive prompts in a single request — seamless and scalable, regardless of the length.
Author-email: Ranjit Das <ranjitdax89@gmail.com>, Uday Subba <udaysubba2004@gmail.com>
Project-URL: Homepage, https://github.com/RanjitDas-IN/tts-accelerator
Project-URL: Issues, https://github.com/RanjitDas-IN/tts-accelerator
Classifier: Programming Language :: Python :: 3
Classifier: License :: OSI Approved :: MIT License
Classifier: Operating System :: OS Independent
Requires-Python: >=3.8
License-File: LICENSE
Requires-Dist: edge_tts
Requires-Dist: sounddevice
Requires-Dist: soundfile
Dynamic: license-file
